CHANGES.txt
LICENSE.txt
MANIFEST.in
README.txt
setup.py
js/__init__.py
js.angular_nvd3_directives.egg-info/PKG-INFO
js.angular_nvd3_directives.egg-info/SOURCES.txt
js.angular_nvd3_directives.egg-info/dependency_links.txt
js.angular_nvd3_directives.egg-info/entry_points.txt
js.angular_nvd3_directives.egg-info/namespace_packages.txt
js.angular_nvd3_directives.egg-info/not-zip-safe
js.angular_nvd3_directives.egg-info/requires.txt
js.angular_nvd3_directives.egg-info/top_level.txt
js/angular_nvd3_directives/__init__.py
js/angular_nvd3_directives/test_angularjs-nvd3-directives.txt
js/angular_nvd3_directives/resources/angularjs-nvd3-directives.js
js/angular_nvd3_directives/resources/angularjs-nvd3-directives.min.js