Metadata-Version: 1.0
Name: js.angular-nvd3-directives
Version: 0.0.7
Summary: Fanstatic packaging of angularjs-nvd3-directives
Home-page: UNKNOWN
Author: Fanstatic Developers
Author-email: fanstatic@googlegroups.com
License: BSD
Platform: UNKNOWN
